freechatgpt/__init__.py
freechatgpt/free_chatgpt.py
freechatgpt/ip_util.py
freechatgpt-1.3.5.dist-info/METADATA
freechatgpt-1.3.5.dist-info/WHEEL
freechatgpt-1.3.5.dist-info/top_level.txt
freechatgpt-1.3.5.dist-info/RECORD
