Metadata-Version: 2.1
Name: freechatgpt
Version: 1.3.5
Summary: free chatgpt api, not need token
Home-page: https://github.com/abo123456789
Author: abo123456789
Author-email: abcdef123456chen@sohu.com
Maintainer: abo123456789
Maintainer-email: abcdef123456chen@sohu.com
License: MIT License
Keywords: chatgpt,free
Platform: all
Classifier: Development Status :: 4 - Beta
Classifier: Operating System :: OS Independent
Classifier: Intended Audience :: Developers
Classifier: License :: OSI Approved :: MIT License
Classifier: Programming Language :: Python
Classifier: Programming Language :: Python :: Implementation
Classifier: Programming Language :: Python :: 3.6
Classifier: Programming Language :: Python :: 3.7
Classifier: Programming Language :: Python :: 3.8
Classifier: Programming Language :: Python :: 3.9
Classifier: Programming Language :: Python :: 3.10
Classifier: Topic :: Software Development :: Libraries
Requires-Dist: requests (>=2.12.3)
Requires-Dist: retrying (>=1.3.3)
Requires-Dist: detool
